License.txt
MANIFEST.in
README.txt
setup.cfg
setup.py
Ancestration.egg-info/PKG-INFO
Ancestration.egg-info/SOURCES.txt
Ancestration.egg-info/dependency_links.txt
Ancestration.egg-info/top_level.txt
Ancestration.egg-info/zip-safe
ancestration/__init__.py
ancestration/_errors.py
ancestration/_family_inheritance.py