Metadata-Version: 1.1
Name: Ancestration
Version: 0.1.0
Summary: Family Inheritance for Python.
Home-page: http://github.com/IvIePhisto/Ancestration
Author: Michael Pohl
Author-email: pohl-michael@gmx.biz
License: MIT
Keywords: family inheritance
Platform: UNKNOWN
Classifier: Development Status :: 4 - Beta
Classifier: Intended Audience :: Developers
Classifier: License :: OSI Approved :: MIT License
Classifier: Programming Language :: Python :: 2.7
Classifier: Programming Language :: Python :: 3.3
Classifier: Topic :: Software Development :: Libraries :: Python Modules
